hspatial/__init__.py
hspatial/cli.py
hspatial/hspatial.py
hspatial/test.py
hspatial-4.1.0.dist-info/LICENSE
hspatial-4.1.0.dist-info/METADATA
hspatial-4.1.0.dist-info/WHEEL
hspatial-4.1.0.dist-info/entry_points.txt
hspatial-4.1.0.dist-info/top_level.txt
hspatial-4.1.0.dist-info/RECORD
