Metadata-Version: 2.1
Name: hspatial
Version: 4.1.0
Summary: Utilities for spatial integration of time series
Home-page: https://github.com/openmeteo/hspatial
Author: Antonis Christofides
Author-email: antonis@antonischristofides.com
License: GNU General Public License v3
Keywords: hspatial
Classifier: Development Status :: 2 - Pre-Alpha
Classifier: Intended Audience :: Developers
Classifier: License :: OSI Approved :: GNU General Public License v3 (GPLv3)
Classifier: Natural Language :: English
Classifier: Programming Language :: Python :: 3.5
Classifier: Programming Language :: Python :: 3.6
License-File: LICENSE
Requires-Dist: Click >=7.0
Requires-Dist: iso8601
Requires-Dist: htimeseries <8,>=6
Requires-Dist: affine
Requires-Dist: simpletail
Requires-Dist: gdal <4,>=1.10
Requires-Dist: django <6,>=2.2
